<?xml version="1.0"?>

<!--********************************************************************
Copyright 2016 Robert A. Beezer

This file is part of MathBook XML.

MathBook XML is free software: you can redistribute it and/or modify
it under the terms of the GNU General Public License as published by
the Free Software Foundation, either version 2 or version 3 of the
License (at your option).

MathBook XML is distributed in the hope that it will be useful,
but WITHOUT ANY WARRANTY; without even the implied warranty of
MERCHANTABILITY or FITNESS FOR A PARTICULAR PURPOSE.  See the
GNU General Public License for more details.

You should have received a copy of the GNU General Public License
along with MathBook XML.  If not, see <http://www.gnu.org/licenses/>.
*********************************************************************-->
<!-- This file was originally part of the book     -->
<!--   Modeling, Functions, and Graphs   -->
<!--           4th                                     -->
<!-- Copyright (C) Katherine Yoshiwara      -->

<exercises xml:id="section-1-2-exercises"  xmlns:xi="http://www.w3.org/2001/XInclude">
    <title>Homework</title>

<exercisegroup>
        <introduction><p>For which of the following pairs is the second quantity a function of the first? Explain your answers.</p></introduction>
    <exercise number="1">
        <statement>
            <p>Price of an item; sales tax on the item at 4<percent/></p>
        </statement>
    </exercise>

    <exercise number="2">
        <statement>
            <p>Time traveled at constant speed; distance traveled</p>
        </statement>
    </exercise>

    <exercise number="3">
        <statement>
            <p>Number of years of education; annual income</p>
        </statement>
    </exercise>

    <exercise number="4">
        <statement>
            <p>Distance flown in an airplane; price of the ticket</p>
        </statement>
   </exercise>

    <exercise number="5">
        <statement>
            <p>Volume of a container of water; the weight of the water</p>
        </statement>
    </exercise>

    <exercise number="6">
        <statement>
            <p>Amount of a paycheck; amount of Social Security tax withheld</p>
        </statement>
    </exercise>
</exercisegroup>


<exercisegroup cols="2">
        <introduction><p>Each of the following objects establishes a correspondence between two variables. Suggest appropriate input and output variables and decide whether the relationship is a function.
        </p></introduction>
    <exercise number="7">
        <statement>
            <p>An itemized grocery receipt</p>
        </statement>
     </exercise>

    <exercise number="8">
        <statement>
            <p>An inventory list</p>
        </statement>
    </exercise>

    <exercise number="9">
        <statement><p>An index          
        </p></statement>
    </exercise>

    <exercise number="10">
        <statement><p>
            A will        
        </p></statement>
    </exercise>

    <exercise number="11">
        <statement><p>
                    An instructor's grade book           
        </p></statement>
    </exercise>

    <exercise number="12">
        <statement><p>
                    An address book           
        </p></statement>
    </exercise>
    <exercise number="13">
        <statement>
            <p>A bathroom scale</p>
        </statement>
    </exercise>

    <exercise number="14">
        <statement>
            <p>A radio dial</p>
            </statement>
    </exercise>
    </exercisegroup>

    <exercisegroup cols="4">
        <introduction><p>
            Which of the following tables define the second variable as a function of the first variable? Explain why or why not.
        </p></introduction>

    <exercise number="15">
        <statement>
            <p>
                <tabular top="major" halign="center" right="minor" left="minor" bottom="minor">
                    <row bottom="minor">
                        <cell><m>x</m></cell>
                        <cell><m>t</m></cell>
                    </row>
                    <row>
                        <cell><m>-1</m></cell>
                        <cell><m>2</m></cell>
                    </row>
                    <row>
                        <cell><m>0</m></cell>
                        <cell><m>9</m></cell>
                    </row>
                    <row>
                        <cell><m>1</m></cell>
                        <cell><m>-2</m></cell>
                    </row>
                    <row>
                        <cell><m>0</m></cell>
                        <cell><m>-3</m></cell>
                    </row>
                    <row>
                        <cell><m>-1</m></cell>
                        <cell><m>5</m></cell>
                    </row>
                </tabular>
            </p>        
        </statement>
    </exercise>

    <exercise number="16">
        <statement>
            <p>
                <tabular top="major" halign="center" right="minor" left="minor" bottom="minor">
                    <row bottom="minor">
                        <cell><m>y</m></cell>
                        <cell><m>w</m></cell>
                    </row>
                    <row>
                        <cell><m>0</m></cell>
                        <cell><m>8</m></cell>
                    </row>
                    <row>
                        <cell><m>1</m></cell>
                        <cell><m>12</m></cell>
                    </row>
                    <row>
                        <cell><m>3</m></cell>
                        <cell><m>7</m></cell>
                    </row>
                    <row>
                        <cell><m>5</m></cell>
                        <cell><m>-3</m></cell>
                    </row>
                    <row>
                        <cell><m>7</m></cell>
                        <cell><m>4</m></cell>
                    </row>
                </tabular>

            </p>
        </statement>
    </exercise>

    <exercise number="17">
        <statement>
            <p>
                <tabular top="major" halign="center" right="minor" left="minor" bottom="minor">
                    <row bottom="minor">
                        <cell><m>x</m></cell>
                        <cell><m>y</m></cell>
                    </row>
                    <row>
                        <cell><m>-3</m></cell>
                        <cell><m>8</m></cell>
                    </row>
                    <row>
                        <cell><m>-2</m></cell>
                        <cell><m>3</m></cell>
                    </row>
                    <row>
                        <cell><m>-1</m></cell>
                        <cell><m>0</m></cell>
                    </row>
                    <row>
                        <cell><m>0</m></cell>
                        <cell><m>-1</m></cell>
                    </row>
                    <row>
                        <cell><m>1</m></cell>
                        <cell><m>0</m></cell>
                    </row>
                    <row>
                        <cell><m>2</m></cell>
                        <cell><m>3</m></cell>
                    </row>
                    <row>
                        <cell><m>3</m></cell>
                        <cell><m>8</m></cell>
                    </row>
                </tabular>
            </p>
        </statement>
    </exercise>

    <exercise number="18">
        <statement>
            <p>
                <tabular top="major" halign="center" right="minor" left="minor" bottom="minor">
                    <row bottom="minor">
                        <cell><m>s</m></cell>
                        <cell><m>t</m></cell>
                    </row>
                    <row>
                        <cell><m>2</m></cell>
                        <cell><m>5</m></cell>
                    </row>
                    <row>
                        <cell><m>4</m></cell>
                        <cell><m>10</m></cell>
                    </row>
                    <row>
                        <cell><m>6</m></cell>
                        <cell><m>15</m></cell>
                    </row>
                    <row>
                        <cell><m>8</m></cell>
                        <cell><m>20</m></cell>
                    </row>
                    <row>
                        <cell><m>6</m></cell>
                        <cell><m>25</m></cell>
                    </row>
                    <row>
                        <cell><m>4</m></cell>
                        <cell><m>30</m></cell>
                    </row>
                    <row>
                        <cell><m>2</m></cell>
                        <cell><m>35</m></cell>
                    </row>
                </tabular>
            </p>
        </statement>
    </exercise>

    </exercisegroup>

<exercisegroup cols="2">
    <exercise number="19">
        <statement>
            <p>
                <tabular top="major" halign="center" right="minor" left="minor" bottom="minor">
                    <row bottom="minor">
                        <cell><m>r</m></cell>
                        <cell><m>-4</m></cell>
                        <cell><m>-2</m></cell>
                        <cell><m>0</m></cell>
                        <cell><m>2</m></cell>
                        <cell><m>4</m></cell>
                    </row>
                    <row>
                        <cell><m>v</m></cell>
                        <cell><m>6</m></cell>
                        <cell><m>6</m></cell>
                        <cell><m>3</m></cell>
                        <cell><m>6</m></cell>
                        <cell><m>8</m></cell>
                    </row>
                </tabular>            
            </p>
        </statement>
    </exercise>

    <exercise number="20">
        <statement>
            <p>
                <tabular top="major" halign="center" right="minor" left="minor" bottom="minor">
                    <row bottom="minor">
                        <cell><m>p</m></cell>
                        <cell><m>-5</m></cell>
                        <cell><m>-4</m></cell>
                        <cell><m>-3</m></cell>
                        <cell><m>-2</m></cell>
                        <cell><m>-1</m></cell>
                    </row>
                    <row>
                        <cell><m>d</m></cell>
                        <cell><m>-5</m></cell>
                        <cell><m>-4</m></cell>
                        <cell><m>-3</m></cell>
                        <cell><m>-2</m></cell>
                        <cell><m>-1</m></cell>
                    </row>

                </tabular>            
            </p>
            </statement>
    </exercise>

    <exercise number="21">
        <statement>
            <p>
                <tabular top="major" halign="center" right="minor" left="minor" bottom="minor">
                    <row bottom="minor">
                        <cell>Pressure (<m>p</m>)</cell>
                        <cell>Volume (<m>v</m>)</cell>
                    </row>
                    <row>
                        <cell><m>15</m></cell>
                        <cell><m>100.0</m></cell>
                    </row>
                    <row>
                        <cell><m>20</m></cell>
                        <cell><m>75.0</m></cell>
                    </row>
                    <row>
                        <cell><m>25</m></cell>
                        <cell><m>60.0</m></cell>
                    </row>
                    <row>
                        <cell><m>30</m></cell>
                        <cell><m>50.0</m></cell>
                    </row>
                    <row>
                        <cell><m>35</m></cell>
                        <cell><m>42.8</m></cell>
                    </row>
                    <row>
                        <cell><m>40</m></cell>
                        <cell><m>37.5</m></cell>
                    </row>
                    <row>
                        <cell><m>45</m></cell>
                        <cell><m>33.3</m></cell>
                    </row>
                    <row>
                        <cell><m>50</m></cell>
                        <cell><m>30.0</m></cell>
                    </row>
                </tabular>
            </p>        
        </statement>
    </exercise>

    <exercise number="22">
        <statement>
            <p>
                <tabular top="major" halign="center" right="minor" left="minor" bottom="minor">
                    <row bottom="minor">
                        <cell>Frequency (<m>f</m>)</cell>
                        <cell>Wavelength (<m>w</m>)</cell>
                    </row>
                    <row>
                        <cell><m>5</m></cell>
                        <cell><m>60.0</m></cell>
                    </row>
                    <row>
                        <cell><m>10</m></cell>
                        <cell><m>30.0</m></cell>
                    </row>
                    <row>
                        <cell><m>20</m></cell>
                        <cell><m>15.0</m></cell>
                    </row>
                    <row>
                        <cell><m>30</m></cell>
                        <cell><m>10.0</m></cell>
                    </row>
                    <row>
                        <cell><m>40</m></cell>
                        <cell><m>7.5</m></cell>
                    </row>
                    <row>
                        <cell><m>50</m></cell>
                        <cell><m>6.0</m></cell>
                    </row>
                    <row>
                        <cell><m>60</m></cell>
                        <cell><m>5.0</m></cell>
                    </row>
                    <row>
                        <cell><m>70</m></cell>
                        <cell><m>4.3</m></cell>
                    </row>
                </tabular>
            </p>
        </statement>
    </exercise>

    <exercise number="23">
        <statement>
            <p>
                <tabular top="major" halign="center" right="minor" left="minor" bottom="minor">
                    <row bottom="minor">
                        <cell>Temperature (<m>T</m>)</cell>
                        <cell>Humidity (<m>h</m>)</cell>
                    </row>
                    <row>
                        <cell>Jan. 1 <m>34\degree</m>F</cell>
                        <cell><m>42\%</m></cell>
                    </row>
                    <row>
                        <cell>Jan. 2 <m>36\degree</m>F</cell>
                        <cell><m>44\%</m></cell>
                    </row>
                    <row>
                        <cell>Jan. 3 <m>35\degree</m>F</cell>
                        <cell><m>47\%</m></cell>
                    </row>
                    <row>
                        <cell>Jan. 4 <m>29\degree</m>F</cell>
                        <cell><m>50\%</m></cell>
                    </row>
                    <row>
                        <cell>Jan. 5 <m>31\degree</m>F</cell>
                        <cell><m>52\%</m></cell>
                    </row>
                    <row>
                        <cell>Jan. 6<m>35\degree</m>F</cell>
                        <cell><m>51%</m></cell>
                    </row>
                    <row>
                        <cell>Jan. 7 <m>34\degree</m>F</cell>
                        <cell><m>49\%</m></cell>
                    </row>
                </tabular>
            </p>
        </statement>
    </exercise>

    <exercise number="24">
        <statement>
            <p>
                <tabular top="major" halign="center" right="minor" left="minor" bottom="minor">
                    <row bottom="minor">
                        <cell><line>Inflation</line><line> rate (<m>I</m>)</line></cell>
                        <cell><line>Unemployment</line><line> rate (<m>U</m>)</line></cell>
                    </row>
                    <row>
                        <cell>1972 <m>\hphantom{000}5.6\%</m></cell>
                        <cell><m>5.1\%</m></cell>
                    </row>
                    <row>
                        <cell>1973 <m>\hphantom{000}6.2\%</m></cell>
                        <cell><m>4.5\%</m></cell>
                    </row>
                    <row>
                        <cell>1974 <m>\hphantom{000}10.1\%</m></cell>
                        <cell><m>4.9\%</m></cell>
                    </row>
                    <row>
                        <cell>1975 <m>\hphantom{000}9.2\%</m></cell>
                        <cell><m>7.4\%</m></cell>
                    </row>
                    <row>
                        <cell>1976 <m>\hphantom{000}5.8\%</m></cell>
                        <cell><m>6.7\%</m></cell>
                    </row>
                    <row>
                        <cell>1977 <m>\hphantom{000}5.6\%</m></cell>
                        <cell><m>6.8\%</m></cell>
                    </row>
                    <row>
                        <cell>1978 <m>\hphantom{000}6.7\%</m></cell>
                        <cell><m>7.4\%</m></cell>
                    </row>
                </tabular>
            </p>
        </statement>
    </exercise>

    </exercisegroup>

    <exercise number="25">
        <statement>
            <p>The owner of a gas station has <m>\$19,200</m> to spend on unleaded gas this month. Regular unleaded costs him <m>\$2.40</m> per gallon, and premium unleaded costs <m>\$3.20</m> per gallon.</p>
            <ol label="*a*">
                <li><p>How much do <m>x</m> gallons of regular cost? How much do <m>y</m> gallons of premium cost?</p></li>
                <li><p>Write an equation in general form that relates the amount of regular unleaded gasoline, <m></m>, the owner can buy and the amount of premium unleaded, <m>y</m>.</p></li>
                <li><p>Find the intercepts and sketch the graph.</p></li>
                <li><p>What do the intercepts tell us about the amount of gasoline the owner can purchase?</p></li>
            </ol>
        </statement>
    </exercise>

    <exercise number="26">
        <statement>
            <p>Five pounds of body fat is equivalent to <m>16,000</m> calories. Carol can burn <m>600</m> calories per hour bicycling and <m>400</m> calories per hour swimming.</p>
            <ol label="*a*">
                <li><p>How many calories will Carol burn in <m></m> hours of cycling? How many calories will she burn in <m>y</m> hours of swimming?</p></li>
                <li><p>Write an equation in general form that relates the number of hours, <m>x</m>, of cycling and the number of hours, <m>y</m>, of swimming Carol needs to perform in order to lose <m>5</m> pounds.</p></li>
                <li><p>Find the intercepts and sketch the graph.</p></li>
                <li><p>What do the intercepts tell us about Carol's exercise program?</p></li>
            </ol>
        </statement>
    </exercise>

    <exercise number="27">
        <statement>
            <p>Delbert must increase his daily potassium intake by <m>1800</m> mg. He decides to eat a combination of figs and bananas, which are both low in sodium. There are <m>9</m> mg potassium per gram of fig, and <m>4</m> mg potassium per gram of banana.</p>
            <ol label="*a*">
                <li><p>How much potassium is in <m>x</m> grams of fig? How much potassium is in <m>y</m> grams of banana?</p></li>
                <li><p>Write an equation in general form that relates the number of grams, <m>x</m>, of fig and the number of grams, <m>y</m>, of banana Delbert needs to get <m>1800</m> mg of potassium.</p></li>
                <li><p>Find the intercepts and sketch the graph.</p></li>
                <li><p>What do the intercepts tell us about Delbert's diet?</p></li>
            </ol>
        </statement>
    </exercise>

    <exercise number="28">
        <statement>
            <p>Leslie plans to invest some money in two CD accounts. The first account pays <m>3.6\%</m> interest per year, and the second account pays <m>2.8\%</m> interest per year. Leslie would like to earn <m>\$500</m> per year on her investment.</p>
            <ol label="*a*">
                <li><p>If Leslie invests <m>x</m> dollars in the first account, how much interest will she earn? How much interest will she earn if she invests <m>y</m> dollars in the second account?</p></li>
                <li><p>Write an equation in general form that relates <m>x</m> and <m>y</m> if Leslie earns <m>\$500</m> interest.</p></li>
                <li><p>Find the intercepts and sketch the graph.</p></li>
                <li><p>What do the intercepts tell us about Leslie's investments?</p></li>
            </ol>
        </statement>
    </exercise>

    <exercise number="29">
        <statement>
            <p>Find the intercepts of the graph for each equation.</p>
            <ol label="*a*" cols="2">
                <li><p><m>\displaystyle{\frac{x}{3}+\frac{y}{5}=1} </m></p></li>
                <li><p><m>\displaystyle{2x − 4y = 1} </m></p></li>
                <li><p><m>\displaystyle{\frac{2x}{5}-\frac{2y}{3}=1} </m></p></li>
                <li><p><m>\displaystyle{\frac{x}{p}+\frac{y}{q}=1} </m></p></li>
            </ol>
            <p>Why is the equation <m>\displaystyle{\frac{x}{a}+\frac{y}{b}=1} </m> called the <term>intercept form</term> for a line?</p>
        </statement>
    </exercise>

    <exercise number="30">
        <statement>
            <p>Write an equation in intercept form (see Problem 29) for the line with the given intercepts. Then write the equation in general form.</p>
            <ol label="*a*" cols="2">
                <li><p><m>(6, 0), (0, 2) </m></p></li>
                <li><p><m>(−3, 0), (0, 8) </m></p></li>
                <li><p><m>\left(\dfrac{3}{4}, 0\right), \left(0, \dfrac{-1}{4}\right) </m></p></li>
                <li><p><m>(v, 0), (0, −w) </m></p></li>
                <li><p><m>\left(\dfrac{1}{H}, 0\right), \left(0, \dfrac{1}{T}\right) </m></p></li>
            </ol>
        </statement>
    </exercise>

    <exercise number="31">
        <statement>
            <p><ol label="*a*">
                <li><p>Find the <m>y</m>-intercept of the line <m>y = mx + b</m>.</p></li>
                <li><p>Find the <m>x</m>-intercept of the line <m>y = mx + b</m>.</p></li>
            </ol></p>
        </statement>
    </exercise>

    <exercise number="32">
        <statement>
            <p><ol label="*a*">
                <li><p>Find the <m>y</m>-intercept of the line <m>Ax + By = C</m>.</p></li>
                <li><p>Find the <m>x</m>-intercept of the line <m>Ax + By = C</m>.</p></li>
            </ol></p>
        </statement>
    </exercise>

    <exercisegroup cols="2">
        <introduction><p>
            Write an equation in general form for each line.
        </p></introduction>
    <exercise number="33">
        <statement>
            <p><image source="images/fig-ex-1-1-33" alt="graph of line" width="80%"/> </p>
        </statement>
    </exercise>

    <exercise number="34">
        <statement>
            <p><image source="images/fig-ex-1-1-34" alt="graph of line" width="80%"/> </p>
        </statement>
    </exercise>

    <exercise number="35">
        <statement>
            <p><image source="images/fig-ex-1-1-35" alt="graph of line" width="80%"/> </p>
        </statement>
    </exercise>

    <exercise number="36">
        <statement>
            <p><image source="images/fig-ex-1-1-36" alt="graph of line" width="80%"/> </p>
        </statement>
    </exercise>
    </exercisegroup>

    <exercisegroup cols="2"><introduction><p>
        For Problems 37–44,
        <ol label="*a*">
            <li><p>Solve each equation for <m>y</m> in terms of <m>x</m>. (See the Algebra Skills Refresher <xref ref="appendix-Linear-Equations-and-Inequalities" autoname="yes"/> to review this skill.)</p></li>
            <li><p>Graph the equation on your calculator in the specified window. (See <xref ref="appendix-b" autoname="yes"/> for help with the graphing calculator.)</p></li>
            <li><p>Make a pencil and paper sketch of the graph. Label the scales on your axes, and the coordinates of the intercepts.</p></li>
        </ol>
    </p></introduction>
    <exercise number="37">
        <statement>
            <p><m>2+y=6</m>
                <md>
                    <mrow>
                        \small{\text{Xmin}} \amp = -10 \amp\amp \small{\text{Ymin}} = -10
                    </mrow>
                    <mrow>
                        \small{\text{Xmax}} \amp = 10 \amp\amp \small{\text{Ymax}} = 10
                    </mrow>
                    <mrow>
                        \small{\text{Xscl}} \amp = 1 \amp\amp \small{\text{Yscl}} = 1
                    </mrow>
                </md>
            </p>
        </statement>
    </exercise>

    <exercise number="38">
        <statement>
            <p><m>8 − y + 3x = 0</m>
                <md>
                    <mrow>
                        \small{\text{Xmin}} \amp = -10 \amp\amp \small{\text{Ymin}} = -10
                    </mrow>
                    <mrow>
                        \small{\text{Xmax}} \amp = 10 \amp\amp \small{\text{Ymax}} = 10
                    </mrow>
                    <mrow>
                        \small{\text{Xscl}} \amp = 1 \amp\amp \small{\text{Yscl}} = 1
                    </mrow>
                </md>
            </p>
        </statement>
    </exercise>

    <exercise number="39">
        <statement>
            <p><m>3x − 4y = 1200</m>
                <md>
                    <mrow>
                        \small{\text{Xmin}} \amp = -1000 \amp\amp \small{\text{Ymin}} = -1000
                    </mrow>
                    <mrow>
                        \small{\text{Xmax}} \amp = 1000 \amp\amp \small{\text{Ymax}} = 1000
                    </mrow>
                    <mrow>
                        \small{\text{Xscl}} \amp = 100 \amp\amp \small{\text{Yscl}} = 100
                    </mrow>
                </md>
            </p>
        </statement>
    </exercise>

    <exercise number="40">
        <statement>
            <p><m>x + 2y = 500</m>
                <md>
                    <mrow>
                        \small{\text{Xmin}} \amp = -1000 \amp\amp \small{\text{Ymin}} = -1000
                    </mrow>
                    <mrow>
                        \small{\text{Xmax}} \amp = 1000 \amp\amp \small{\text{Ymax}} = 1000
                    </mrow>
                    <mrow>
                        \small{\text{Xscl}} \amp = 100 \amp\amp \small{\text{Yscl}} = 100
                    </mrow>
               </md>
            </p>
        </statement>
    </exercise>

    <exercise number="41">
        <statement>
            <p><m>0.2x + 5y = 0.1</m>
                <md>
                    <mrow>
                        \small{\text{Xmin}} \amp = -1 \amp\amp \small{\text{Ymin}} = -0.1
                    </mrow>
                    <mrow>
                        \small{\text{Xmax}} \amp = 1 \amp\amp \small{\text{Ymax}} = 0.1
                    </mrow>
                    <mrow>
                        \small{\text{Xscl}} \amp = 0.1 \amp\amp \small{\text{Yscl}} = 0.01
                    </mrow>
                </md>
            </p>
        </statement>
    </exercise>

    <exercise number="42">
        <statement>
            <p><m>1.2x − 4.2y = 3.6</m>
                <md>
                    <mrow>
                        \small{\text{Xmin}} \amp = -1 \amp\amp \small{\text{Ymin}} = -1
                    </mrow>
                    <mrow>
                        \small{\text{Xmax}} \amp = 4 \amp\amp \small{\text{Ymax}} = 1
                    </mrow>
                    <mrow>
                        \small{\text{Xscl}} \amp = 0.2 \amp\amp \small{\text{Yscl}} = 0.1
                    </mrow>
               </md>
            </p>
        </statement>
    </exercise>

    <exercise number="43">
        <statement>
            <p><m>70x + 3y = y + 420</m>
                <md>
                    <mrow>
                        \small{\text{Xmin}} \amp = 0 \amp\amp \small{\text{Ymin}} = 0
                    </mrow>
                    <mrow>
                        \small{\text{Xmax}} \amp = 10 \amp\amp \small{\text{Ymax}} = 250
                    </mrow>
                    <mrow>
                        \small{\text{Xscl}} \amp = 1 \amp\amp \small{\text{Yscl}} = 25
                    </mrow>
                </md>
            </p>
        </statement>
    </exercise>

    <exercise number="44">
        <statement>
            <p><m>40y − 5x = 780 − 20y</m>
                <md>
                     <mrow>
                        \small{\text{Xmin}} \amp = -200 \amp\amp \small{\text{Ymin}} = 0
                    </mrow>
                    <mrow>
                        \small{\text{Xmax}} \amp = 0 \amp\amp \small{\text{Ymax}} = 20
                    </mrow>
                    <mrow>
                        \small{\text{Xscl}} \amp = 20 \amp\amp \small{\text{Yscl}} = 2
                    </mrow>
               </md>
            </p>
        </statement>
    </exercise>

    </exercisegroup>

    <exercisegroup cols="2"><introduction><p>
        For Problems 45–52,
        <ol label="*a*">
            <li><p>Find the <n>x</n>- and <m>y</m>-intercepts.</p></li>
            <li><p>Solve the equation for <m>y</m>.</p></li>
            <li><p>Choose a graphing window in which both intercepts are visible, and graph the equation on your calculator.</p></li>
        </ol>
    </p></introduction>
    <exercise number="45">
        <statement>
            <p><m>x + 4y = 100</m> </p>
        </statement>
    </exercise>

    <exercise number="46">
        <statement>
            <p><m>2x − 3y = −72</m></p>
        </statement>
    </exercise>
    <exercise number="47">
        <statement>
            <p><m>25x − 20y = 1</m> </p>
        </statement>
    </exercise>

    <exercise number="48">
        <statement>
            <p><m>4x + 75y = 60,000</m></p>
        </statement>
    </exercise>

    <exercise number="49">
        <statement>
            <p><m>\dfrac{y}{12} − \dfrac{x}{60}= 1</m> </p>
        </statement>
    </exercise>

    <exercise number="50">
        <statement>
            <p><m>\dfrac{x}{80} + \dfrac{y}{400}= 1</m></p>
        </statement>
    </exercise>
    <exercise number="51">
        <statement>
            <p><m>−2x = 3y + 84</m> </p>
        </statement>
    </exercise>

    <exercise number="52">
        <statement>
            <p><m>7x = 91 − 13y</m></p>
        </statement>
    </exercise>

    </exercisegroup>


</exercises>
